pybr/__init__.py
pybr-0.0.1.dist-info/LICENSE
pybr-0.0.1.dist-info/METADATA
pybr-0.0.1.dist-info/WHEEL
pybr-0.0.1.dist-info/RECORD
